src/single_bank_memory.vhd
library IEEE;
use IEEE.std_logic_1164.all;
use IEEE.numeric_std.all;

-- i_state is the state of the register bank it could be 
-- "0" : IDLE : Bank retains the memory but allows only read but no write operation is allowed.
-- "1" : Active : Bank is fully operational performs read and write.

entity SingleBankMemory is 
    generic (
        MEM_WIDTH : integer := 32;
        MEM_DEPTH : integer := 1024
    );
    port (
        i_clk : in std_ulogic;
        i_nrst : in std_ulogic;
        i_state : in std_ulogic;
        i_write_enable : in std_ulogic;
        i_read_enable : in std_ulogic;
        i_address : in std_ulogic_vector(9 downto 0);
        i_write_data : in std_ulogic_vector(31 downto 0);
        o_read_data : out std_ulogic_vector(31 downto 0)
    );
end entity SingleBankMemory;

architecture RTL of SingleBankMemory is 
    type tMemory is array(0 to MEM_DEPTH-1) of std_ulogic_vector(MEM_WIDTH-1 downto 0); 
    signal MemoryArray : tMemory := (others => (others => '0'));

    begin 

    proc_mem_access : process(i_clk) 
        begin 
            if (rising_edge(i_clk)) then 
                if(i_nrst = '0') then 
                    MemoryArray <= (others => (others => '0'));
                    o_read_data <= (others => '0');
                else 
                    case (i_state) is 
                        when '0' =>
                            -- IDLE
                            if(i_read_enable = '1') then 
                                o_read_data <= MemoryArray(to_integer(unsigned(i_address)));
                            end if;
                        when '1' =>
                            -- Active 
                            if(i_read_enable = '1' and i_write_enable = '1') then 
                                MemoryArray(to_integer(unsigned(i_address))) <= i_write_data;
                                o_read_data <= MemoryArray(to_integer(unsigned(i_address)));
                                --o_read_data <= i_write_data;
                            elsif(i_read_enable = '1' and i_write_enable = '0') then 
                                o_read_data <= MemoryArray(to_integer(unsigned(i_address)));
                            elsif(i_read_enable = '0' and i_write_enable = '1') then 
                                MemoryArray(to_integer(unsigned(i_address))) <= i_write_data;
                            end if;
                        when others => 
                            null;
                    end case;
                end if;
            end if;             
        end process proc_mem_access;
end architecture RTL;

src/multi_bank_memory.vhd
library IEEE;
use IEEE.std_logic_1164.all;
use IEEE.numeric_std.all;

entity MultiBankMemory is 
    generic (
        MEM_WIDTH  : integer := 32;
        MEM_DEPTH  : integer := 1024;
        BANK_COUNT : integer := 4
    );
    port (
        i_clk : in std_ulogic;
        i_nrst : in std_ulogic;
        i_state : in std_ulogic_vector(1 downto 0);
        i_write_enable : in std_ulogic;
        i_read_enable : in std_ulogic;
        i_address : in std_ulogic_vector(11 downto 0);
        i_write_data : in std_ulogic_vector(MEM_WIDTH-1 downto 0);
        o_read_data : out std_ulogic_vector(MEM_WIDTH-1 downto 0)
    );
end entity MultiBankMemory;

architecture RTL of MultiBankMemory is 
    type t_bank_signals is record 
        clk_en    : std_ulogic;
        write_en  : std_ulogic;
        read_en   : std_ulogic;
    end record;

    type t_control_signal is array(0 to BANK_COUNT-1) of t_bank_signals;
    signal control_signals : t_control_signal;

    type t_bank_read_data is array(0 to BANK_COUNT-1) of std_ulogic_vector(MEM_WIDTH-1 downto 0); 
    signal bank_read_data : t_bank_read_data := (others => (others => '0'));

    signal sel_d : std_ulogic_vector(1 downto 0);

    type t_clk_array is array(0 to BANK_COUNT-1) of std_ulogic;
    signal clk_array : t_clk_array := (others => '0');

begin

    gen_clocks: for i in 0 to BANK_COUNT-1 generate
        clk_array(i) <= i_clk and control_signals(i).clk_en and i_state(1);
    end generate gen_clocks;

    gen_banks: for i in 0 to BANK_COUNT-1 generate
        BANK : entity work.SingleBankMemory(RTL)
            generic map (
                MEM_WIDTH => MEM_WIDTH,
                MEM_DEPTH => MEM_DEPTH
            )
            port map (
                i_clk => clk_array(i),
                i_nrst => i_nrst,
                i_state => i_state(0),
                i_write_enable => control_signals(i).write_en,
                i_read_enable => control_signals(i).read_en,
                i_address => i_address(9 downto 0),
                i_write_data => i_write_data,
                o_read_data => bank_read_data(i)
            );
    end generate gen_banks;

    process(i_clk) 
    begin 
        if rising_edge(i_clk) then 
            if (i_nrst = '0') then 
                for i in 0 to BANK_COUNT-1 loop
                    control_signals(i).clk_en <= '0';
                    control_signals(i).write_en <= '0';
                    control_signals(i).read_en <= '0';
                end loop;

            else 
                sel_d <= i_address(11 downto 10);
                for i in 0 to BANK_COUNT-1 loop
                    if (i = to_integer(unsigned(i_address(11 downto 10)))) then
                        control_signals(i).clk_en <= '1';  
                        control_signals(i).write_en <= i_write_enable;
                        control_signals(i).read_en <= i_read_enable;
                    else
                        control_signals(i).clk_en <= '0';     
                        control_signals(i).write_en <= '0';      
                        control_signals(i).read_en <= '0';       
                    end if;
                end loop;
            end if;
        end if;
    end process;
    o_read_data <= bank_read_data(to_integer(unsigned(sel_d)));
end architecture RTL;

sim/tb_multi_bank_memory.vhd
library IEEE;
use IEEE.std_logic_1164.all;
use IEEE.numeric_std.all;

entity tb is
end entity tb;

architecture behavior of tb is
    signal clk         : std_ulogic := '0';
    signal nrst        : std_ulogic := '0';
    signal state       : std_ulogic_vector(1 downto 0) := "11";  -- start with both active
    signal write_enable: std_ulogic := '0';
    signal read_enable : std_ulogic := '0';
    signal address     : std_ulogic_vector(11 downto 0) := (others => '0');
    signal write_data  : std_ulogic_vector(31 downto 0) := (others => '0');
    signal read_data   : std_ulogic_vector(31 downto 0);

    constant clk_period : time := 10 ns;

    component MultiBankMemory is
        generic (
            MEM_WIDTH  : integer := 32;
            MEM_DEPTH  : integer := 1024;
            BANK_COUNT : integer := 4
        );
        port (
            i_clk         : in  std_ulogic;
            i_nrst        : in  std_ulogic;
            i_state       : in  std_ulogic_vector(1 downto 0);
            i_write_enable: in  std_ulogic;
            i_read_enable : in  std_ulogic;
            i_address     : in  std_ulogic_vector(11 downto 0);
            i_write_data  : in  std_ulogic_vector(MEM_WIDTH-1 downto 0);
            o_read_data   : out std_ulogic_vector(MEM_WIDTH-1 downto 0)
        );
    end component;

begin
    uut: MultiBankMemory
        port map (
            i_clk          => clk,
            i_nrst         => nrst,
            i_state        => state,
            i_write_enable => write_enable,
            i_read_enable  => read_enable,
            i_address      => address,
            i_write_data   => write_data,
            o_read_data    => read_data
        );

    clk_process : process
    begin
        while true loop
            clk <= '0'; wait for clk_period/2;
            clk <= '1'; wait for clk_period/2;
        end loop;
    end process;

    stim_process : process
    begin
        nrst <= '0';
        wait for 2*clk_period;
        nrst <= '1';
        wait for clk_period;

        -- Phase 1: state = "11", both read and write enabled
        read_enable  <= '1';
        write_enable <= '1';

        -- Bank 0 (000...)
        address <= "000000000000"; write_data <= x"AAAAAAAA"; wait for clk_period;
        address <= "000000000001"; write_data <= x"BBBBBBBB"; wait for clk_period;
        address <= "000000000010"; write_data <= x"CCCCCCCC"; wait for clk_period;
        -- Overwrite bank0 addr0
        address <= "000000000000"; write_data <= x"DEADBEEF"; wait for clk_period;

        -- Bank 1 (010...)
        address <= "010000000000"; write_data <= x"11111111"; wait for clk_period;
        address <= "010000000001"; write_data <= x"22222222"; wait for clk_period;
        address <= "010000000010"; write_data <= x"33333333"; wait for clk_period;
        -- Overwrite bank1 addr1
        address <= "010000000001"; write_data <= x"CAFEBABE"; wait for clk_period;

        -- Bank 2 (100...)
        address <= "100000000000"; write_data <= x"44444444"; wait for clk_period;
        address <= "100000000001"; write_data <= x"55555555"; wait for clk_period;
        address <= "100000000010"; write_data <= x"66666666"; wait for clk_period;
        -- Overwrite bank2 addr2
        address <= "100000000010"; write_data <= x"12345678"; wait for clk_period;

        -- Bank 3 (110...)
        address <= "110000000000"; write_data <= x"77777777"; wait for clk_period;
        address <= "110000000001"; write_data <= x"88888888"; wait for clk_period;
        address <= "110000000010"; write_data <= x"99999999"; wait for clk_period;
        -- Overwrite bank3 addr1
        address <= "110000000001"; write_data <= x"87654321"; wait for clk_period;
        -- Phase 2: state = "01" (read only)
        write_enable <= '0';
        read_enable  <= '1';
        state <= "01";
        address <= "000000000000"; wait for clk_period;
        address <= "010000000001"; wait for clk_period;
        address <= "100000000010"; wait for clk_period;
        address <= "110000000001"; wait for clk_period;
        -- Phase 3: state = "10" (write only)
        write_enable <= '1';
        read_enable  <= '0';
        state <= "10";
        address <= "000000000011"; write_data <= x"F0F0F0F0"; wait for clk_period;
        address <= "010000000011"; write_data <= x"0F0F0F0F"; wait for clk_period;
        address <= "100000000011"; write_data <= x"A5A5A5A5"; wait for clk_period;
        address <= "110000000011"; write_data <= x"5A5A5A5A"; wait for clk_period;

        -- Phase 4: state = "00" (idle, neither read nor write)
        write_enable <= '0';
        read_enable  <= '0';
        state <= "00";
        address <= "000000000000"; wait for clk_period;
        address <= "010000000000"; wait for clk_period;
        address <= "100000000000"; wait for clk_period;
        address <= "110000000000"; wait for clk_period;

        
        -- Phase 5: Mix states quickly (all combos visible)
        -- state 11 again
        state <= "11"; write_enable <= '1'; read_enable <= '1';
        address <= "000000000100"; write_data <= x"ABCDABCD"; wait for clk_period;

        -- state 01
        state <= "01"; write_enable <= '0'; read_enable <= '1';
        address <= "000000000100"; wait for clk_period;

        -- state 10
        state <= "10"; write_enable <= '1'; read_enable <= '0';
        address <= "010000000100"; write_data <= x"13572468"; wait for clk_period;

        -- state 00
        state <= "00"; write_enable <= '0'; read_enable <= '0';
        address <= "010000000100"; wait for clk_period;

        wait for 100 ns;
        wait;
    end process;
end architecture behavior;

sim/work/result.vcd
$date
  Thu Aug 21 16:18:58 2025
$end
$version
  GHDL v0
$end
$timescale
  1 fs
$end
$scope module standard $end
$upscope $end
$scope module std_logic_1164 $end
$upscope $end
$scope module numeric_std $end
$upscope $end
$scope module tb $end
$var reg 1 ! clk $end
$var reg 1 " nrst $end
$var reg 2 # state[1:0] $end
$var reg 1 $ write_enable $end
$var reg 1 % read_enable $end
$var reg 12 & address[11:0] $end
$var reg 32 ' write_data[31:0] $end
$var reg 32 ( read_data[31:0] $end
$scope module uut $end
$var reg 1 ) i_clk $end
$var reg 1 * i_nrst $end
$var reg 2 + i_state[1:0] $end
$var reg 1 , i_write_enable $end
$var reg 1 - i_read_enable $end
$var reg 12 . i_address[11:0] $end
$var reg 32 / i_write_data[31:0] $end
$var reg 32 0 o_read_data[31:0] $end
$comment control_signals is not handled $end
$comment bank_read_data is not handled $end
$var reg 2 1 sel_d[1:0] $end
$var reg 4 2 clk_array[0:3] $end
$scope module gen_clocks(0) $end
$upscope $end
$scope module gen_clocks(1) $end
$upscope $end
$scope module gen_clocks(2) $end
$upscope $end
$scope module gen_clocks(3) $end
$upscope $end
$scope module gen_banks(0) $end
$scope module bank $end
$var reg 1 3 i_clk $end
$var reg 1 4 i_nrst $end
$var reg 1 5 i_state $end
$var reg 1 6 i_write_enable $end
$var reg 1 7 i_read_enable $end
$var reg 10 8 i_address[9:0] $end
$var reg 32 9 i_write_data[31:0] $end
$var reg 32 : o_read_data[31:0] $end
$comment memoryarray is not handled $end
$upscope $end
$upscope $end
$scope module gen_banks(1) $end
$scope module bank $end
$var reg 1 ; i_clk $end
$var reg 1 < i_nrst $end
$var reg 1 = i_state $end
$var reg 1 > i_write_enable $end
$var reg 1 ? i_read_enable $end
$var reg 10 @ i_address[9:0] $end
$var reg 32 A i_write_data[31:0] $end
$var reg 32 B o_read_data[31:0] $end
$comment memoryarray is not handled $end
$upscope $end
$upscope $end
$scope module gen_banks(2) $end
$scope module bank $end
$var reg 1 C i_clk $end
$var reg 1 D i_nrst $end
$var reg 1 E i_state $end
$var reg 1 F i_write_enable $end
$var reg 1 G i_read_enable $end
$var reg 10 H i_address[9:0] $end
$var reg 32 I i_write_data[31:0] $end
$var reg 32 J o_read_data[31:0] $end
$comment memoryarray is not handled $end
$upscope $end
$upscope $end
$scope module gen_banks(3) $end
$scope module bank $end
$var reg 1 K i_clk $end
$var reg 1 L i_nrst $end
$var reg 1 M i_state $end
$var reg 1 N i_write_enable $end
$var reg 1 O i_read_enable $end
$var reg 10 P i_address[9:0] $end
$var reg 32 Q i_write_data[31:0] $end
$var reg 32 R o_read_data[31:0] $end
$comment memoryarray is not handled $end
$upscope $end
$upscope $end
$upscope $end
$upscope $end
$enddefinitions $end
#0
0!
0"
b11 #
0$
0%
b000000000000 &
b00000000000000000000000000000000 '
bUUUUUUUUUUUUUUUUUUUUUUUUUUUUUUUU (
0)
0*
b11 +
0,
0-
b000000000000 .
b00000000000000000000000000000000 /
bUUUUUUUUUUUUUUUUUUUUUUUUUUUUUUUU 0
bUU 1
b0000 2
03
04
15
U6
U7
b0000000000 8
b00000000000000000000000000000000 9
bUUUUUUUUUUUUUUUUUUUUUUUUUUUUUUUU :
0;
0<
1=
U>
U?
b0000000000 @
b00000000000000000000000000000000 A
bUUUUUUUUUUUUUUUUUUUUUUUUUUUUUUUU B
0C
0D
1E
UF
UG
b0000000000 H
b00000000000000000000000000000000 I
bUUUUUUUUUUUUUUUUUUUUUUUUUUUUUUUU J
0K
0L
1M
UN
UO
b0000000000 P
b00000000000000000000000000000000 Q
bUUUUUUUUUUUUUUUUUUUUUUUUUUUUUUUU R
#5000000
1!
1)
b0000 2
03
06
07
0;
0>
0?
0C
0F
0G
0K
0N
0O
#10000000
0!
0)
#15000000
1!
1)
#20000000
0!
1"
0)
1*
14
1<
1D
1L
#25000000
1!
1)
b00 1
b1000 2
13
#30000000
0!
1$
1%
b10101010101010101010101010101010 '
0)
1,
1-
b10101010101010101010101010101010 /
b0000 2
03
b10101010101010101010101010101010 9
b10101010101010101010101010101010 A
b10101010101010101010101010101010 I
b10101010101010101010101010101010 Q
#35000000
1!
b00000000000000000000000000000000 (
1)
b00000000000000000000000000000000 0
b1000 2
13
16
17
b00000000000000000000000000000000 :
#40000000
0!
b000000000001 &
b10111011101110111011101110111011 '
0)
b000000000001 .
b10111011101110111011101110111011 /
b0000 2
03
b0000000001 8
b10111011101110111011101110111011 9
b0000000001 @
b10111011101110111011101110111011 A
b0000000001 H
b10111011101110111011101110111011 I
b0000000001 P
b10111011101110111011101110111011 Q
#45000000
1!
1)
b1000 2
13
#50000000
0!
b000000000010 &
b11001100110011001100110011001100 '
0)
b000000000010 .
b11001100110011001100110011001100 /
b0000 2
03
b0000000010 8
b11001100110011001100110011001100 9
b0000000010 @
b11001100110011001100110011001100 A
b0000000010 H
b11001100110011001100110011001100 I
b0000000010 P
b11001100110011001100110011001100 Q
#55000000
1!
1)
b1000 2
13
#60000000
0!
b000000000000 &
b11011110101011011011111011101111 '
0)
b000000000000 .
b11011110101011011011111011101111 /
b0000 2
03
b0000000000 8
b11011110101011011011111011101111 9
b0000000000 @
b11011110101011011011111011101111 A
b0000000000 H
b11011110101011011011111011101111 I
b0000000000 P
b11011110101011011011111011101111 Q
#65000000
1!
b10101010101010101010101010101010 (
1)
b10101010101010101010101010101010 0
b1000 2
13
b10101010101010101010101010101010 :
#70000000
0!
b010000000000 &
b00010001000100010001000100010001 '
0)
b010000000000 .
b00010001000100010001000100010001 /
b0000 2
03
b00010001000100010001000100010001 9
b00010001000100010001000100010001 A
b00010001000100010001000100010001 I
b00010001000100010001000100010001 Q
#75000000
1!
b00000000000000000000000000000000 (
1)
b00000000000000000000000000000000 0
b01 1
b0100 2
03
06
07
1;
1>
1?
b00000000000000000000000000000000 B
#80000000
0!
b010000000001 &
b00100010001000100010001000100010 '
0)
b010000000001 .
b00100010001000100010001000100010 /
b0000 2
b0000000001 8
b00100010001000100010001000100010 9
0;
b0000000001 @
b00100010001000100010001000100010 A
b0000000001 H
b00100010001000100010001000100010 I
b0000000001 P
b00100010001000100010001000100010 Q
#85000000
1!
1)
b0100 2
1;
#90000000
0!
b010000000010 &
b00110011001100110011001100110011 '
0)
b010000000010 .
b00110011001100110011001100110011 /
b0000 2
b0000000010 8
b00110011001100110011001100110011 9
0;
b0000000010 @
b00110011001100110011001100110011 A
b0000000010 H
b00110011001100110011001100110011 I
b0000000010 P
b00110011001100110011001100110011 Q
#95000000
1!
1)
b0100 2
1;
#100000000
0!
b010000000001 &
b11001010111111101011101010111110 '
0)
b010000000001 .
b11001010111111101011101010111110 /
b0000 2
b0000000001 8
b11001010111111101011101010111110 9
0;
b0000000001 @
b11001010111111101011101010111110 A
b0000000001 H
b11001010111111101011101010111110 I
b0000000001 P
b11001010111111101011101010111110 Q
#105000000
1!
b00100010001000100010001000100010 (
1)
b00100010001000100010001000100010 0
b0100 2
1;
b00100010001000100010001000100010 B
#110000000
0!
b100000000000 &
b01000100010001000100010001000100 '
0)
b100000000000 .
b01000100010001000100010001000100 /
b0000 2
b0000000000 8
b01000100010001000100010001000100 9
0;
b0000000000 @
b01000100010001000100010001000100 A
b0000000000 H
b01000100010001000100010001000100 I
b0000000000 P
b01000100010001000100010001000100 Q
#115000000
1!
b00000000000000000000000000000000 (
1)
b00000000000000000000000000000000 0
b10 1
b0010 2
0;
0>
0?
1C
1F
1G
b00000000000000000000000000000000 J
#120000000
0!
b100000000001 &
b01010101010101010101010101010101 '
0)
b100000000001 .
b01010101010101010101010101010101 /
b0000 2
b0000000001 8
b01010101010101010101010101010101 9
b0000000001 @
b01010101010101010101010101010101 A
0C
b0000000001 H
b01010101010101010101010101010101 I
b0000000001 P
b01010101010101010101010101010101 Q
#125000000
1!
1)
b0010 2
1C
#130000000
0!
b100000000010 &
b01100110011001100110011001100110 '
0)
b100000000010 .
b01100110011001100110011001100110 /
b0000 2
b0000000010 8
b01100110011001100110011001100110 9
b0000000010 @
b01100110011001100110011001100110 A
0C
b0000000010 H
b01100110011001100110011001100110 I
b0000000010 P
b01100110011001100110011001100110 Q
#135000000
1!
1)
b0010 2
1C
#140000000
0!
b00010010001101000101011001111000 '
0)
b00010010001101000101011001111000 /
b0000 2
b00010010001101000101011001111000 9
b00010010001101000101011001111000 A
0C
b00010010001101000101011001111000 I
b00010010001101000101011001111000 Q
#145000000
1!
b01100110011001100110011001100110 (
1)
b01100110011001100110011001100110 0
b0010 2
1C
b01100110011001100110011001100110 J
#150000000
0!
b110000000000 &
b01110111011101110111011101110111 '
0)
b110000000000 .
b01110111011101110111011101110111 /
b0000 2
b0000000000 8
b01110111011101110111011101110111 9
b0000000000 @
b01110111011101110111011101110111 A
0C
b0000000000 H
b01110111011101110111011101110111 I
b0000000000 P
b01110111011101110111011101110111 Q
#155000000
1!
b00000000000000000000000000000000 (
1)
b00000000000000000000000000000000 0
b11 1
b0001 2
0C
0F
0G
1K
1N
1O
b00000000000000000000000000000000 R
#160000000
0!
b110000000001 &
b10001000100010001000100010001000 '
0)
b110000000001 .
b10001000100010001000100010001000 /
b0000 2
b0000000001 8
b10001000100010001000100010001000 9
b0000000001 @
b10001000100010001000100010001000 A
b0000000001 H
b10001000100010001000100010001000 I
0K
b0000000001 P
b10001000100010001000100010001000 Q
#165000000
1!
1)
b0001 2
1K
#170000000
0!
b110000000010 &
b10011001100110011001100110011001 '
0)
b110000000010 .
b10011001100110011001100110011001 /
b0000 2
b0000000010 8
b10011001100110011001100110011001 9
b0000000010 @
b10011001100110011001100110011001 A
b0000000010 H
b10011001100110011001100110011001 I
0K
b0000000010 P
b10011001100110011001100110011001 Q
#175000000
1!
1)
b0001 2
1K
#180000000
0!
b110000000001 &
b10000111011001010100001100100001 '
0)
b110000000001 .
b10000111011001010100001100100001 /
b0000 2
b0000000001 8
b10000111011001010100001100100001 9
b0000000001 @
b10000111011001010100001100100001 A
b0000000001 H
b10000111011001010100001100100001 I
0K
b0000000001 P
b10000111011001010100001100100001 Q
#185000000
1!
b10001000100010001000100010001000 (
1)
b10001000100010001000100010001000 0
b0001 2
1K
b10001000100010001000100010001000 R
#190000000
0!
b01 #
0$
b000000000000 &
0)
b01 +
0,
b000000000000 .
b0000 2
b0000000000 8
b0000000000 @
b0000000000 H
0K
b0000000000 P
#195000000
1!
b10101010101010101010101010101010 (
1)
b10101010101010101010101010101010 0
b00 1
17
0N
0O
#200000000
0!
b010000000001 &
0)
b010000000001 .
b0000000001 8
b0000000001 @
b0000000001 H
b0000000001 P
#205000000
1!
b00100010001000100010001000100010 (
1)
b00100010001000100010001000100010 0
b01 1
07
1?
#210000000
0!
b100000000010 &
0)
b100000000010 .
b0000000010 8
b0000000010 @
b0000000010 H
b0000000010 P
#215000000
1!
b01100110011001100110011001100110 (
1)
b01100110011001100110011001100110 0
b10 1
0?
1G
#220000000
0!
b110000000001 &
0)
b110000000001 .
b0000000001 8
b0000000001 @
b0000000001 H
b0000000001 P
#225000000
1!
b10001000100010001000100010001000 (
1)
b10001000100010001000100010001000 0
b11 1
0G
1O
#230000000
0!
b10 #
1$
0%
b000000000011 &
b11110000111100001111000011110000 '
0)
b10 +
1,
0-
b000000000011 .
b11110000111100001111000011110000 /
05
b0000000011 8
b11110000111100001111000011110000 9
0=
b0000000011 @
b11110000111100001111000011110000 A
0E
b0000000011 H
b11110000111100001111000011110000 I
0M
b0000000011 P
b11110000111100001111000011110000 Q
#235000000
1!
b10101010101010101010101010101010 (
1)
b10101010101010101010101010101010 0
b00 1
b1000 2
13
16
0K
0O
#240000000
0!
b010000000011 &
b00001111000011110000111100001111 '
0)
b010000000011 .
b00001111000011110000111100001111 /
b0000 2
03
b00001111000011110000111100001111 9
b00001111000011110000111100001111 A
b00001111000011110000111100001111 I
b00001111000011110000111100001111 Q
#245000000
1!
b00100010001000100010001000100010 (
1)
b00100010001000100010001000100010 0
b01 1
b0100 2
03
06
1;
1>
#250000000
0!
b100000000011 &
b10100101101001011010010110100101 '
0)
b100000000011 .
b10100101101001011010010110100101 /
b0000 2
b10100101101001011010010110100101 9
0;
b10100101101001011010010110100101 A
b10100101101001011010010110100101 I
b10100101101001011010010110100101 Q
#255000000
1!
b01100110011001100110011001100110 (
1)
b01100110011001100110011001100110 0
b10 1
b0010 2
0;
0>
1C
1F
#260000000
0!
b110000000011 &
b01011010010110100101101001011010 '
0)
b110000000011 .
b01011010010110100101101001011010 /
b0000 2
b01011010010110100101101001011010 9
b01011010010110100101101001011010 A
0C
b01011010010110100101101001011010 I
b01011010010110100101101001011010 Q
#265000000
1!
b10001000100010001000100010001000 (
1)
b10001000100010001000100010001000 0
b11 1
b0001 2
0C
0F
1K
1N
#270000000
0!
b00 #
0$
b000000000000 &
0)
b00 +
0,
b000000000000 .
b0000 2
b0000000000 8
b0000000000 @
b0000000000 H
0K
b0000000000 P
#275000000
1!
b10101010101010101010101010101010 (
1)
b10101010101010101010101010101010 0
b00 1
0N
#280000000
0!
b010000000000 &
0)
b010000000000 .
#285000000
1!
b00100010001000100010001000100010 (
1)
b00100010001000100010001000100010 0
b01 1
#290000000
0!
b100000000000 &
0)
b100000000000 .
#295000000
1!
b01100110011001100110011001100110 (
1)
b01100110011001100110011001100110 0
b10 1
#300000000
0!
b110000000000 &
0)
b110000000000 .
#305000000
1!
b10001000100010001000100010001000 (
1)
b10001000100010001000100010001000 0
b11 1
#310000000
0!
b11 #
1$
1%
b000000000100 &
b10101011110011011010101111001101 '
0)
b11 +
1,
1-
b000000000100 .
b10101011110011011010101111001101 /
15
b0000000100 8
b10101011110011011010101111001101 9
1=
b0000000100 @
b10101011110011011010101111001101 A
1E
b0000000100 H
b10101011110011011010101111001101 I
1M
b0000000100 P
b10101011110011011010101111001101 Q
#315000000
1!
b00000000000000000000000000000000 (
1)
b00000000000000000000000000000000 0
b00 1
b1000 2
13
16
17
b00000000000000000000000000000000 :
0K
#320000000
0!
b01 #
0$
0)
b01 +
0,
b0000 2
03
#325000000
1!
1)
06
#330000000
0!
b10 #
1$
0%
b010000000100 &
b00010011010101110010010001101000 '
0)
b10 +
1,
0-
b010000000100 .
b00010011010101110010010001101000 /
05
b00010011010101110010010001101000 9
0=
b00010011010101110010010001101000 A
0E
b00010011010101110010010001101000 I
0M
b00010011010101110010010001101000 Q
#335000000
1!
b00100010001000100010001000100010 (
1)
b00100010001000100010001000100010 0
b01 1
b0100 2
03
07
1;
1>
#340000000
0!
b00 #
0$
0)
b00 +
0,
b0000 2
0;
#345000000
1!
1)
0>
